fairylandlogger/__init__.py
fairylandlogger/_appenders.py
fairylandlogger/_enums.py
fairylandlogger/_registry.py
fairylandlogger/_structure.py
fairylandlogger/logger.py
pypi_fairylandlogger-1.0.3.dist-info/licenses/LICENSE
pypi_fairylandlogger-1.0.3.dist-info/METADATA
pypi_fairylandlogger-1.0.3.dist-info/WHEEL
pypi_fairylandlogger-1.0.3.dist-info/top_level.txt
pypi_fairylandlogger-1.0.3.dist-info/RECORD
