Metadata-Version: 2.4
Name: pypi-fairylandlogger
Version: 1.0.3
Summary: A comprehensive Python package for FairylandLogger project
Author-email: FairylandTech <fairylandfuture@protonmail.com>
License: GNU General Public License v3 (GPLv3)
Project-URL: Homepage, https://github.com/FairylandTech/pypi-fairylandlogger
Project-URL: Repository, https://github.com/FairylandTech/pypi-fairylandlogger
Project-URL: Documentation, https://github.com/FairylandTech/pypi-fairylandfuture#readme
Project-URL: Issues, https://github.com/FairylandTech/pypi-fairylandfuture/issues
Keywords: fairylandlogger,fairyland,logger,logging,python,loguru,log
Classifier: Development Status :: 4 - Beta
Classifier: Intended Audience :: Developers
Classifier: License :: OSI Approved :: GNU General Public License v3 (GPLv3)
Classifier: Programming Language :: Python :: 3
Classifier: Programming Language :: Python :: 3.12
Requires-Python: >=3.12
License-File: LICENSE
Requires-Dist: loguru
Requires-Dist: pyyaml
Provides-Extra: dev
Requires-Dist: build; extra == "dev"
Requires-Dist: twine; extra == "dev"
Requires-Dist: ruff; extra == "dev"
Requires-Dist: pytest; extra == "dev"
Dynamic: license-file
